pyquark/__init__.py
pyquark/main.py
pyquark-0.0.1.dist-info/LICENSE
pyquark-0.0.1.dist-info/METADATA
pyquark-0.0.1.dist-info/WHEEL
pyquark-0.0.1.dist-info/top_level.txt
pyquark-0.0.1.dist-info/RECORD
