Metadata-Version: 2.1
Name: pyquark
Version: 0.0.1
Summary: A package containing useful bits and bobs.
Home-page: https://github.com/pypa/sampleproject
Author: Code06
Author-email: pdannootdev@gmail.com
License: UNKNOWN
Project-URL: Bug Tracker, https://github.com/pypa/sampleproject/issues
Platform: UNKNOWN
Classifier: Programming Language :: Python :: 3
Classifier: License :: OSI Approved :: MIT License
Classifier: Operating System :: OS Independent
Requires-Python: >=3.9
License-File: LICENSE
